[
  {
    "OBJHTMID": 1,
    "地区NO": 1,
    "カルテ地区": "木下地区",
    "番号": 1,
    "名称": "木下小学校",
    "所在地": "印西市木下1502",
    "電話番号": "42-2607",
    "震災": "○",
    "風水害": "○",
    "土砂": "",
    "種別": "指定避難場所・避難所",
    "経度": 140.15450549759,
    "緯度": 35.8394159833445,
    "分類": "指定避難所"
  },
  {
    "OBJHTMID": 2,
    "地区NO": 1,
    "カルテ地区": "木下地区",
    "番号": 21,
    "名称": "平岡自然公園",
    "所在地": "印西市平岡1554",
    "電話番号": "42-1008",
    "震災": "○",
    "風水害": "○",
    "土砂": "",
    "種別": "指定避難場所・避難所",
    "経度": 140.170755530498,
    "緯度": 35.8269570314788,
    "分類": "指定避難所"
  },
  {
    "OBJHTMID": 3,
    "地区NO": 2,
    "カルテ地区": "大森地区",
    "番号": 3,
    "名称": "大森小学校",
    "所在地": "印西市大森3350",
    "電話番号": "42-2089",
    "震災": "○",
    "風水害": "",
    "土砂": "",
    "種別": "指定避難場所・避難所",
    "経度": 140.140874458939,
    "緯度": 35.8365250081175,
    "分類": "指定避難所"
  },
  {
    "OBJHTMID": 4,
    "地区NO": 2,
    "カルテ地区": "大森地区",
    "番号": 14,
    "名称": "印西中学校",
    "所在地": "印西市大森2244",
    "電話番号": "42-3151",
    "震災": "○",
    "風水害": "○",
    "土砂": "",
    "種別": "指定避難場所・避難所",
    "経度": 140.147418442254,
    "緯度": 35.8281340343697,
    "分類": "指定避難所"
  },
  {
    "OBJHTMID": 5,
    "地区NO": 3,
    "カルテ地区": "小林地区",
    "番号": 2,
    "名称": "小林小学校",
    "所在地": "印西市小林2554",
    "電話番号": "42-4311",
    "震災": "○",
    "風水害": "○",
    "土砂": "",
    "種別": "指定避難場所・避難所",
    "経度": 140.187006652455,
    "緯度": 35.8310150220869,
    "分類": "指定避難所"
  },
  {
    "OBJHTMID": 6,
    "地区NO": 3,
    "カルテ地区": "小林地区",
    "番号": 9,
    "名称": "小林北小学校",
    "所在地": "印西市小林北5-1-5",
    "電話番号": "97-1100",
    "震災": "○",
    "風水害": "",
    "土砂": "",
    "種別": "指定避難場所・避難所",
    "経度": 140.198630746857,
    "緯度": 35.8316400268953,
    "分類": "指定避難所"
  },
  {
    "OBJHTMID": 7,
    "地区NO": 3,
    "カルテ地区": "小林地区",
    "番号": 17,
    "名称": "小林中学校",
    "所在地": "印西市小林大門下1-4-1",
    "電話番号": "97-3100",
    "震災": "○",
    "風水害": "○",
    "土砂": "",
    "種別": "指定避難場所・避難所",
    "経度": 140.186542612024,
    "緯度": 35.8232300504443,
    "分類": "指定避難所"
  },
  {
    "OBJHTMID": 8,
    "地区NO": 4,
    "カルテ地区": "永治地区",
    "番号": 5,
    "名称": "旧永治小学校",
    "所在地": "印西市浦部557",
    "電話番号": "42-5111",
    "震災": "○",
    "風水害": "○",
    "土砂": "",
    "種別": "指定避難場所・避難所",
    "経度": 140.107937434758,
    "緯度": 35.8240811126666,
    "分類": "指定避難所"
  },
  {
    "OBJHTMID": 9,
    "地区NO": 5,
    "カルテ地区": "千葉ニュータウン地区",
    "番号": 6,
    "名称": "木刈小学校",
    "所在地": "印西市木刈2-6",
    "電話番号": "46-1755",
    "震災": "○",
    "風水害": "○",
    "土砂": "",
    "種別": "指定避難場所・避難所",
    "経度": 140.106727360715,
    "緯度": 35.8103421555946,
    "分類": "指定避難所"
  },
  {
    "OBJHTMID": 10,
    "地区NO": 5,
    "カルテ地区": "千葉ニュータウン地区",
    "番号": 7,
    "名称": "内野小学校",
    "所在地": "印西市内野1-1",
    "電話番号": "46-1781",
    "震災": "○",
    "風水害": "○",
    "土砂": "",
    "種別": "指定避難場所・避難所",
    "経度": 140.124954276141,
    "緯度": 35.7979811712098,
    "分類": "指定避難所"
  },
  {
    "OBJHTMID": 11,
    "地区NO": 5,
    "カルテ地区": "千葉ニュータウン地区",
    "番号": 8,
    "名称": "原山小学校",
    "所在地": "印西市原山3-4",
    "電話番号": "46-1701",
    "震災": "○",
    "風水害": "○",
    "土砂": "",
    "種別": "指定避難場所・避難所",
    "経度": 140.130649292778,
    "緯度": 35.7998021594822,
    "分類": "指定避難所"
  },
  {
    "OBJHTMID": 12,
    "地区NO": 5,
    "カルテ地区": "千葉ニュータウン地区",
    "番号": 10,
    "名称": "小倉台小学校",
    "所在地": "印西市小倉台2-3",
    "電話番号": "46-5711",
    "震災": "○",
    "風水害": "○",
    "土砂": "",
    "種別": "指定避難場所・避難所",
    "経度": 140.109377320374,
    "緯度": 35.8043381691382,
    "分類": "指定避難所"
  },
  {
    "OBJHTMID": 13,
    "地区NO": 5,
    "カルテ地区": "千葉ニュータウン地区",
    "番号": 11,
    "名称": "高花小学校",
    "所在地": "印西市高花2-4",
    "電話番号": "46-6211",
    "震災": "○",
    "風水害": "○",
    "土砂": "",
    "種別": "指定避難場所・避難所",
    "経度": 140.13868228463,
    "緯度": 35.7970181640452,
    "分類": "指定避難所"
  },
  {
    "OBJHTMID": 14,
    "地区NO": 5,
    "カルテ地区": "千葉ニュータウン地区",
    "番号": 15,
    "名称": "船穂中学校",
    "所在地": "印西市高花1-3",
    "電話番号": "46-0021",
    "震災": "○",
    "風水害": "○",
    "土砂": "",
    "種別": "指定避難場所・避難所",
    "経度": 140.132422267023,
    "緯度": 35.795342175156,
    "分類": "指定避難所"
  },
  {
    "OBJHTMID": 15,
    "地区NO": 5,
    "カルテ地区": "千葉ニュータウン地区",
    "番号": 16,
    "名称": "木刈中学校",
    "所在地": "印西市木刈2-1",
    "電話番号": "46-1751",
    "震災": "○",
    "風水害": "○",
    "土砂": "",
    "種別": "指定避難場所・避難所",
    "経度": 140.109857339098,
    "緯度": 35.8073641596077,
    "分類": "指定避難所"
  },
  {
    "OBJHTMID": 16,
    "地区NO": 5,
    "カルテ地区": "千葉ニュータウン地区",
    "番号": 18,
    "名称": "原山中学校",
    "所在地": "印西市原山1-2",
    "電話番号": "46-6911",
    "震災": "○",
    "風水害": "○",
    "土砂": "",
    "種別": "指定避難場所・避難所",
    "経度": 140.12762728342,
    "緯度": 35.7987431661157,
    "分類": "指定避難所"
  },
  {
    "OBJHTMID": 17,
    "地区NO": 6,
    "カルテ地区": "牧の原・草深地区",
    "番号": 12,
    "名称": "西の原小学校",
    "所在地": "印西市西の原2-7",
    "電話番号": "45-0150",
    "震災": "○",
    "風水害": "○",
    "土砂": "",
    "種別": "指定避難場所・避難所",
    "経度": 140.152196333978,
    "緯度": 35.8003411446365,
    "分類": "指定避難所"
  },
  {
    "OBJHTMID": 18,
    "地区NO": 6,
    "カルテ地区": "牧の原・草深地区",
    "番号": 13,
    "名称": "原小学校",
    "所在地": "印西市原3-5",
    "電話番号": "45-8611",
    "震災": "○",
    "風水害": "○",
    "土砂": "",
    "種別": "指定避難場所・避難所",
    "経度": 140.163676369026,
    "緯度": 35.7994651434377,
    "分類": "指定避難所"
  },
  {
    "OBJHTMID": 19,
    "地区NO": 6,
    "カルテ地区": "牧の原・草深地区",
    "番号": 19,
    "名称": "西の原中学校",
    "所在地": "印西市西の原1-3",
    "電話番号": "45-0160",
    "震災": "○",
    "風水害": "○",
    "土砂": "",
    "種別": "指定避難場所・避難所",
    "経度": 140.156670364244,
    "緯度": 35.803401129385,
    "分類": "指定避難所"
  },
  {
    "OBJHTMID": 20,
    "地区NO": 6,
    "カルテ地区": "牧の原・草深地区",
    "番号": 20,
    "名称": "そうふけふれあいの里",
    "所在地": "印西市草深924",
    "電話番号": "47-4700",
    "震災": "○",
    "風水害": "○",
    "土砂": "",
    "種別": "指定避難場所・避難所",
    "経度": 140.150820303138,
    "緯度": 35.7956471641524,
    "分類": "指定避難所"
  },
  {
    "OBJHTMID": 21,
    "地区NO": 6,
    "カルテ地区": "牧の原・草深地区",
    "番号": 34,
    "名称": "滝野小学校",
    "所在地": "印西市滝野5-1",
    "電話番号": "97-1977",
    "震災": "○",
    "風水害": "○",
    "土砂": "",
    "種別": "指定避難場所・避難所",
    "経度": 140.175806475077,
    "緯度": 35.8090701025011,
    "分類": "指定避難所"
  },
  {
    "OBJHTMID": 22,
    "地区NO": 6,
    "カルテ地区": "牧の原・草深地区",
    "番号": 35,
    "名称": "滝野中学校",
    "所在地": "印西市滝野5-2",
    "電話番号": "97-1988",
    "震災": "○",
    "風水害": "○",
    "土砂": "",
    "種別": "指定避難場所・避難所",
    "経度": 140.1749004671,
    "緯度": 35.8085001047664,
    "分類": "指定避難所"
  },
  {
    "OBJHTMID": 23,
    "地区NO": 7,
    "カルテ地区": "宗像地区",
    "番号": 27,
    "名称": "旧宗像小学校",
    "所在地": "印西市岩戸１６８０",
    "電話番号": "42-5111",
    "震災": "○",
    "風水害": "○",
    "土砂": "",
    "種別": "指定避難場所・避難所",
    "経度": 140.168463163493,
    "緯度": 35.7634932888154,
    "分類": "指定避難所"
  },
  {
    "OBJHTMID": 24,
    "地区NO": 8,
    "カルテ地区": "船穂地区",
    "番号": 4,
    "名称": "船穂小学校",
    "所在地": "印西市船尾1292",
    "電話番号": "46-0023",
    "震災": "○",
    "風水害": "○",
    "土砂": "",
    "種別": "指定避難場所・避難所",
    "経度": 140.128818188237,
    "緯度": 35.7837312217364,
    "分類": "指定避難所"
  },
  {
    "OBJHTMID": 25,
    "地区NO": 12,
    "カルテ地区": "本埜第一地区",
    "番号": 31,
    "名称": "本埜小学校",
    "所在地": "印西市中根1281-2",
    "電話番号": "97-0035",
    "震災": "○",
    "風水害": "○",
    "土砂": "",
    "種別": "指定避難場所・避難所",
    "経度": 140.194745578811,
    "緯度": 35.8066471129014,
    "分類": "指定避難所"
  },
  {
    "OBJHTMID": 26,
    "地区NO": 12,
    "カルテ地区": "本埜第一地区",
    "番号": 33,
    "名称": "本埜中学校",
    "所在地": "印西市笠神250",
    "電話番号": "97-0009",
    "震災": "○",
    "風水害": "○",
    "土砂": "",
    "種別": "指定避難場所・避難所",
    "経度": 140.199017664031,
    "緯度": 35.8164620782885,
    "分類": "指定避難所"
  },
  {
    "OBJHTMID": 27,
    "地区NO": 13,
    "カルテ地区": "本埜第二地区",
    "番号": 32,
    "名称": "旧本埜第二小学校",
    "所在地": "印西市笠神1745",
    "電話番号": "42-5111",
    "震災": "○",
    "風水害": "",
    "土砂": "",
    "種別": "指定避難場所・避難所",
    "経度": 140.214723856972,
    "緯度": 35.8274200520252,
    "分類": "指定避難所"
  },
  {
    "OBJHTMID": 28,
    "地区NO": 11,
    "カルテ地区": "いには野地区",
    "番号": 26,
    "名称": "印旛中学校",
    "所在地": "印西市舞姫2-1-1",
    "電話番号": "98-0711",
    "震災": "○",
    "風水害": "○",
    "土砂": "",
    "種別": "指定避難場所・避難所",
    "経度": 140.204833506941,
    "緯度": 35.7850891864004,
    "分類": "指定避難所"
  },
  {
    "OBJHTMID": 29,
    "地区NO": 11,
    "カルテ地区": "いには野地区",
    "番号": 29,
    "名称": "いには野小学校",
    "所在地": "印西市若萩3-9-1",
    "電話番号": "98-2080",
    "震災": "○",
    "風水害": "○",
    "土砂": "",
    "種別": "指定避難場所・避難所",
    "経度": 140.207508556297,
    "緯度": 35.7897551695623,
    "分類": "指定避難所"
  },
  {
    "OBJHTMID": 30,
    "地区NO": 9,
    "カルテ地区": "六合地区",
    "番号": 22,
    "名称": "六合小学校",
    "所在地": "印西市瀬戸1580",
    "電話番号": "98-0006",
    "震災": "○",
    "風水害": "○",
    "土砂": "",
    "種別": "指定避難場所・避難所",
    "経度": 140.227737605187,
    "緯度": 35.7776711948231,
    "分類": "指定避難所"
  },
  {
    "OBJHTMID": 31,
    "地区NO": 10,
    "カルテ地区": "平賀地区",
    "番号": 28,
    "名称": "平賀小学校",
    "所在地": "印西市平賀1161-2",
    "電話番号": "98-1151",
    "震災": "○",
    "風水害": "○",
    "土砂": "",
    "種別": "指定避難場所・避難所",
    "経度": 140.246967539672,
    "緯度": 35.7550522204503,
    "分類": "指定避難所"
  },
  {
    "OBJHTMID": 33,
    "地区NO": 6,
    "カルテ地区": "草深・牧の原・滝野地区",
    "番号": 36,
    "名称": "牧の原小学校",
    "所在地": "牧の原3-1-1",
    "電話番号": "29-5560",
    "震災": "○",
    "風水害": "○",
    "土砂": "",
    "種別": "指定避難場所・避難所",
    "経度": 140.160868341106,
    "緯度": 35.8121321969293,
    "分類": "指定避難所"
  }
]
